{
    "English": [
        {
            "id":"English - 1",
            "name":"yayaya",
            "lang":"English",
            "version":"1.0.2",
            "iconUrl":"https://github.com/nyagami/LNReader-plugins/blob/master/icons/indonesian/test.png?raw=true",
            "url":"https://raw.githubusercontent.com/nyagami/LNReader-plugins/master/plugins/english/test.js?newtest=true",
            "description": "This is description for plugin"
        },
        {
            "id":"English - 2",
            "name":"Absolute Url",
            "lang":"English",
            "version":"1.0.7",
            "iconUrl":"https://github.com/nyagami/LNReader-plugins/blob/master/icons/english/painful.png?raw=true",
            "url":"https://raw.githubusercontent.com/nyagami/LNReader-plugins/master/plugins/english/LightNovelReader.js?newtest=true",
            "description": "This is description for plugin"
        }
    ],
    "Bahasa Indonesia": [
        {   
            "id":"Bahasa Indonesia - 1",
            "name": "test",
            "lang": "Bahasa Indonesia",
            "version": "1.0.0",
            "iconUrl": "https://github.com/nyagami/LNReader-plugins/blob/master/icons/indonesian/test.png?raw=true",
            "url": "https://raw.githubusercontent.com/nyagami/LNReader-plugins/master/plugins/indonesian/test.js?newtest=true",
            "description": "This is description for plugin"
        }
    ],
    "Tiếng Việt": [
        {
            "id":"Tiếng Việt - 1",
            "name": "Hako.re",
            "lang": "Tiếng Việt",
            "version": "1.0.15",
            "iconUrl": "https://github.com/nyagami/LNReader-plugins/blob/master/icons/vietnamese/chie_panik.png?raw=true",
            "url": "https://raw.githubusercontent.com/nyagami/LNReader-plugins/master/plugins/vietnamese/hako.js?newtest=true",
            "description": "This is description for plugin"
        }
    ]
}